{"__symbolic":"module","version":4,"metadata":{"AjfTimeModel":{"__symbolic":"class","members":{"toString":[{"__symbolic":"method"}],"fromString":[{"__symbolic":"method"}]}},"AjfTimeModule":{"__symbolic":"class","decorators":[{"__symbolic":"call","expression":{"__symbolic":"reference","module":"@angular/core","name":"NgModule","line":27,"character":1},"arguments":[{"imports":[{"__symbolic":"reference","module":"@angular/forms","name":"FormsModule","line":29,"character":4}],"declarations":[{"__symbolic":"reference","name":"AjfTime"}],"exports":[{"__symbolic":"reference","name":"AjfTime"}]}]}],"members":{}},"AJF_TIME_CONTROL_VALUE_ACCESSOR":{"provide":{"__symbolic":"reference","module":"@angular/forms","name":"NG_VALUE_ACCESSOR","line":28,"character":11},"useExisting":{"__symbolic":"reference","name":"AjfTime"},"multi":true},"AjfTime":{"__symbolic":"class","decorators":[{"__symbolic":"call","expression":{"__symbolic":"reference","module":"@angular/core","name":"Component","line":33,"character":1},"arguments":[{"moduleId":{"__symbolic":"select","expression":{"__symbolic":"reference","name":"module"},"member":"id"},"selector":"ajf-time","providers":[{"__symbolic":"reference","name":"AJF_TIME_CONTROL_VALUE_ACCESSOR"}],"encapsulation":{"__symbolic":"select","expression":{"__symbolic":"reference","module":"@angular/core","name":"ViewEncapsulation","line":39,"character":17},"member":"None"},"changeDetection":{"__symbolic":"select","expression":{"__symbolic":"reference","module":"@angular/core","name":"ChangeDetectionStrategy","line":40,"character":19},"member":"OnPush"},"template":"<div><input min=\"0\" max=\"24\" [(ngModel)]=\"hours\" type=\"number\" (ngModelChange)=\"hours = $event\"> <input min=\"0\" max=\"60\" [(ngModel)]=\"minutes\" type=\"number\" (ngModelChange)=\"minutes = $event\"></div>","styles":[""]}]}],"members":{"__ctor__":[{"__symbolic":"constructor"}],"writeValue":[{"__symbolic":"method"}],"registerOnChange":[{"__symbolic":"method"}],"registerOnTouched":[{"__symbolic":"method"}]}}},"origins":{"AjfTimeModel":"./time-model","AjfTimeModule":"./time-module","AJF_TIME_CONTROL_VALUE_ACCESSOR":"./time","AjfTime":"./time"},"importAs":"@ajf/material/time"}